README.md
setup.cfg
setup.py
test/test_actualize_api.py
test/test_actualize_settings.py
test/test_actualize_task.py
test/test_advanced_location.py
test/test_analytics_api.py
test/test_analytics_check_group_type.py
test/test_analytics_check_settings.py
test/test_analytics_check_settings_far_location.py
test/test_analytics_check_settings_far_order.py
test/test_analytics_check_settings_huge_peak_load.py
test/test_analytics_check_settings_lack_capacity.py
test/test_analytics_check_settings_lack_resource.py
test/test_analytics_check_settings_low_order_compatibility.py
test/test_analytics_check_settings_low_resource_compatibility.py
test/test_analytics_check_settings_short_time_window.py
test/test_analytics_check_type.py
test/test_analytics_task.py
test/test_analytics_unplanned_highlight.py
test/test_analytics_unplanned_result.py
test/test_analytics_unplanned_settings.py
test/test_analytics_unplanned_task.py
test/test_assigned_shift.py
test/test_box.py
test/test_calculation_detail.py
test/test_capacity.py
test/test_capacity_factor.py
test/test_cargo.py
test/test_cargo_placement.py
test/test_check_result.py
test/test_compatibility_penalty.py
test/test_convert_api.py
test/test_convert_settings.py
test/test_convert_task.py
test/test_demand.py
test/test_demand_fact.py
test/test_facts.py
test/test_hardlink.py
test/test_hardlink_element.py
test/test_inline_response400.py
test/test_inline_response401.py
test/test_inline_response403.py
test/test_inline_response404.py
test/test_inline_response406.py
test/test_inline_response415.py
test/test_inline_response429.py
test/test_inline_response500.py
test/test_inline_response501.py
test/test_inline_response502.py
test/test_inline_response503.py
test/test_inline_response504.py
test/test_inline_response_default.py
test/test_job_type.py
test/test_load_window.py
test/test_location.py
test/test_measurements.py
test/test_model_break.py
test/test_objects_metrics.py
test/test_order.py
test/test_order_fact.py
test/test_performer.py
vrt_lss_lastmile.egg-info/PKG-INFO
vrt_lss_lastmile.egg-info/SOURCES.txt
vrt_lss_lastmile.egg-info/dependency_links.txt
vrt_lss_lastmile.egg-info/requires.txt
vrt_lss_lastmile.egg-info/top_level.txt
