Metadata-Version: 1.0
Name: vrt-lss-lastmile
Version: 3.15.183137
Summary: Veeroute.Lastmile
Home-page: https://docs.veeroute.com/#/lss/lastmile
Author: Veeroute Support Team
Author-email: support@veeroute.com
License: UNKNOWN
Keywords: OpenAPI,OpenAPI-Generator,Veeroute.Lastmile
Platform: UNKNOWN
